rocksdb_py-0.0.6.dist-info/METADATA
rocksdb_py-0.0.6.dist-info/WHEEL
rocksdbpy/__init__.py
rocksdbpy/__init__.pyi
rocksdbpy/py.typed
rocksdbpy/rocksdbpy.cp39-win_amd64.pyd
rocksdb_py-0.0.6.dist-info/RECORD
