Metadata-Version: 2.4
Name: rocksdb-py
Version: 0.0.6
Summary: Python bindings for RocksDB
Keywords: rocksdb,rocksdb-py
Author-email: Tarik Yilmaz <tarikyilmaz.54@gmail.com>
License: Apache-2.0
